
select *
from (
  select
    t.opcode,
    (select name from opcode where id=t.opcode),
    t.args,
    (select fullmethodname from cp_methodref_view where methodrefid=t.args),
    count(*) as cc
  from (
    select c.opcode, c.args
    from (
      select opcodeindex-1 as opcodeindex from code
      where opcode=(select id from opcode where name='checkcast')
    ) t
    left join code c on c.opcodeindex=t.opcodeindex
  ) t
  group by opcode, args
)
order by cc desc
limit 100
;
opcode|(select name from opcode where id=t.opcode)|args|(select fullmethodname from cp_methodref_view where methodrefid=t.args)|cc
43|aload_1|||7920558
185|invokeinterface|1021|java/util/Iterator.next()Ljava/lang/Object;|3927771
44|aload_2|||2314394
83|aastore|||1322685
185|invokeinterface|934|java/util/Map.get(Ljava/lang/Object;)Ljava/lang/Object;|1290221
185|invokeinterface|2194|java/util/List.get(I)Ljava/lang/Object;|1153310
42|aload_0|||1040508
45|aload_3|||975912
182|invokevirtual|53906|scala/Option.get()Ljava/lang/Object;|526377
25|aload|4|java/lang/System.exit(I)V|521535
50|aaload|||517777
184|invokestatic|26711|java/lang/Enum.valueOf(Ljava/lang/Class;Ljava/lang/String;)Ljava/lang/Enum;|441101
185|invokeinterface|3158|java/util/Map$Entry.getValue()Ljava/lang/Object;|434477
182|invokevirtual|53910|scala/Tuple2._2()Ljava/lang/Object;|424207
182|invokevirtual|53909|scala/Tuple2._1()Ljava/lang/Object;|415368
185|invokeinterface|3157|java/util/Map$Entry.getKey()Ljava/lang/Object;|366611
25|aload|5|HTTPClient/URI.<init>(Ljava/lang/String;)V|358523
182|invokevirtual|195634|clojure/lang/Var.getRawRoot()Ljava/lang/Object;|340785
184|invokestatic|173139|org/codehaus/groovy/runtime/ScriptBytecodeAdapter.castToType(Ljava/lang/Object;Ljava/lang/Class;)Ljava/lang/Object;|300929
184|invokestatic|195627|clojure/lang/RT.var(Ljava/lang/String;Ljava/lang/String;)Lclojure/lang/Var;|296335
185|invokeinterface|25850|org/apache/xmlbeans/impl/values/TypeStore.find_element_user(Ljavax/xml/namespace/QName;I)Lorg/apache/xmlbeans/impl/values/TypeStoreUser;|264359
1|aconst_null|||250048
25|aload|6|MyAuthPrompter.<init>(Ljava/lang/String;Ljava/lang/String;)V|240446
182|invokevirtual|2694|java/util/ArrayList.get(I)Ljava/lang/Object;|209778
182|invokevirtual|1163|java/util/HashMap.get(Ljava/lang/Object;)Ljava/lang/Object;|209565
25|aload|7|HTTPClient/DefaultAuthHandler.setAuthorizationPrompter(LHTTPClient/AuthorizationPrompter;)LHTTPClient/AuthorizationPrompter;|194659
184|invokestatic|179231|com/google/common/base/Preconditions.checkNotNull(Ljava/lang/Object;)Ljava/lang/Object;|193665
185|invokeinterface|25861|org/apache/xmlbeans/impl/values/TypeStore.find_attribute_user(Ljavax/xml/namespace/QName;)Lorg/apache/xmlbeans/impl/values/TypeStoreUser;|191306
180|getfield|41043|com/sun/org/apache/bcel/internal/generic/BranchInstruction.notifyTarget(Lcom/sun/org/apache/bcel/internal/generic/InstructionHandle;Lcom/sun/org/apache/bcel/internal/generic/InstructionHandle;Lcom/sun/org/apache/bcel/internal/generic/InstructionTargeter;)V|186519
185|invokeinterface|25851|org/apache/xmlbeans/impl/values/TypeStore.add_element_user(Ljavax/xml/namespace/QName;)Lorg/apache/xmlbeans/impl/values/TypeStoreUser;|178960
185|invokeinterface|54002|scala/Function1.apply(Ljava/lang/Object;)Ljava/lang/Object;|165433
185|invokeinterface|3541|java/util/List.toArray([Ljava/lang/Object;)[Ljava/lang/Object;|159594
185|invokeinterface|83|java/util/Enumeration.nextElement()Ljava/lang/Object;|150752
25|aload|8|HTTPClient/HTTPConnection.<init>(LHTTPClient/URI;)V|145074
182|invokevirtual|14815|java/lang/ref/SoftReference.get()Ljava/lang/Object;|142777
192|checkcast|194|java/io/FileWriter.<init>(Ljava/lang/String;)V|113391
25|aload|9|HTTPClient/URI.getPathAndQuery()Ljava/lang/String;|109894
182|invokevirtual|61348|scala/Some.x()Ljava/lang/Object;|108912
182|invokevirtual|84864|shapeless/$colon$colon.tail()Lshapeless/HList;|106315
182|invokevirtual|67|java/util/Hashtable.get(Ljava/lang/Object;)Ljava/lang/Object;|100459
182|invokevirtual|5102|java/lang/ThreadLocal.get()Ljava/lang/Object;|99259
185|invokeinterface|25863|org/apache/xmlbeans/impl/values/TypeStore.add_attribute_user(Ljavax/xml/namespace/QName;)Lorg/apache/xmlbeans/impl/values/TypeStoreUser;|96282
182|invokevirtual|423|java/util/Vector.elementAt(I)Ljava/lang/Object;|95551
185|invokeinterface|158347|org/eclipse/emf/common/util/EList.get(I)Ljava/lang/Object;|95295
182|invokevirtual|54160|scala/collection/immutable/$colon$colon.head()Ljava/lang/Object;|94912
182|invokevirtual|54251|scala/Option.getOrElse(Lscala/Function0;)Ljava/lang/Object;|90738
182|invokevirtual|78334|scala/Predef$.implicitly(Ljava/lang/Object;)Ljava/lang/Object;|87142
183|invokespecial|348|java/lang/Object.clone()Ljava/lang/Object;|86297
185|invokeinterface|53874|scala/Function0.apply()Ljava/lang/Object;|82749
182|invokevirtual|53859|scala/collection/immutable/List.map(Lscala/Function1;Lscala/collection/generic/CanBuildFrom;)Ljava/lang/Object;|82727
182|invokevirtual|81452|scala/Some.get()Ljava/lang/Object;|80702
182|invokevirtual|636|java/lang/Class.newInstance()Ljava/lang/Object;|79809
184|invokestatic|195684|clojure/lang/RT.map([Ljava/lang/Object;)Lclojure/lang/IPersistentMap;|78413
25|aload|10|HTTPClient/HTTPConnection.Head(Ljava/lang/String;)LHTTPClient/HTTPResponse;|78326
184|invokestatic|189902|org/codehaus/groovy/runtime/typehandling/ShortTypeHandling.castToString(Ljava/lang/Object;)Ljava/lang/String;|77265
192|checkcast|166|sun/net/ProgressData.unregister(Lsun/net/ProgressEntry;)V|76100
184|invokestatic|195629|clojure/lang/RT.keyword(Ljava/lang/String;Ljava/lang/String;)Lclojure/lang/Keyword;|74984
185|invokeinterface|25834|org/apache/xmlbeans/SchemaTypeLoader.newInstance(Lorg/apache/xmlbeans/SchemaType;Lorg/apache/xmlbeans/XmlOptions;)Lorg/apache/xmlbeans/XmlObject;|73942
185|invokeinterface|53871|scala/collection/TraversableLike.map(Lscala/Function1;Lscala/collection/generic/CanBuildFrom;)Ljava/lang/Object;|73245
182|invokevirtual|54013|scala/collection/immutable/Map$.apply(Lscala/collection/Seq;)Lscala/collection/GenMap;|72546
184|invokestatic|1195133|org/apache/hadoop/yarn/webapp/hamlet/HamletImpl.setSelector(Lorg/apache/hadoop/yarn/webapp/hamlet/HamletSpec$CoreAttrs;Ljava/lang/String;)Lorg/apache/hadoop/yarn/webapp/hamlet/HamletSpec$CoreAttrs;|68601
182|invokevirtual|81464|scala/reflect/api/Names$TermNameExtractor.apply(Ljava/lang/String;)Lscala/reflect/api/Names$TermNameApi;|67166
182|invokevirtual|61047|scala/collection/Seq$.apply(Lscala/collection/Seq;)Lscala/collection/GenTraversable;|65481
185|invokeinterface|61402|scala/collection/Seq.map(Lscala/Function1;Lscala/collection/generic/CanBuildFrom;)Ljava/lang/Object;|64712
25|aload|11|HTTPClient/HTTPResponse.getStatusCode()I|64210
182|invokevirtual|62832|java/lang/invoke/SerializedLambda.getCapturedArg(I)Ljava/lang/Object;|64048
182|invokevirtual|70112|java/util/concurrent/atomic/AtomicReference.get()Ljava/lang/Object;|62738
184|invokestatic|12451|java/security/AccessController.doPrivileged(Ljava/security/PrivilegedAction;)Ljava/lang/Object;|56330
184|invokestatic|195628|clojure/lang/Symbol.intern(Ljava/lang/String;Ljava/lang/String;)Lclojure/lang/Symbol;|55377
182|invokevirtual|173304|groovy/lang/Reference.get()Ljava/lang/Object;|55214
185|invokeinterface|25835|org/apache/xmlbeans/SchemaTypeLoader.parse(Ljava/lang/String;Lorg/apache/xmlbeans/SchemaType;Lorg/apache/xmlbeans/XmlOptions;)Lorg/apache/xmlbeans/XmlObject;|52809
185|invokeinterface|25836|org/apache/xmlbeans/SchemaTypeLoader.parse(Ljava/io/File;Lorg/apache/xmlbeans/SchemaType;Lorg/apache/xmlbeans/XmlOptions;)Lorg/apache/xmlbeans/XmlObject;|52808
185|invokeinterface|25837|org/apache/xmlbeans/SchemaTypeLoader.parse(Ljava/net/URL;Lorg/apache/xmlbeans/SchemaType;Lorg/apache/xmlbeans/XmlOptions;)Lorg/apache/xmlbeans/XmlObject;|52808
185|invokeinterface|25838|org/apache/xmlbeans/SchemaTypeLoader.parse(Ljava/io/InputStream;Lorg/apache/xmlbeans/SchemaType;Lorg/apache/xmlbeans/XmlOptions;)Lorg/apache/xmlbeans/XmlObject;|52808
185|invokeinterface|25839|org/apache/xmlbeans/SchemaTypeLoader.parse(Ljava/io/Reader;Lorg/apache/xmlbeans/SchemaType;Lorg/apache/xmlbeans/XmlOptions;)Lorg/apache/xmlbeans/XmlObject;|52808
185|invokeinterface|25841|org/apache/xmlbeans/SchemaTypeLoader.parse(Lorg/w3c/dom/Node;Lorg/apache/xmlbeans/SchemaType;Lorg/apache/xmlbeans/XmlOptions;)Lorg/apache/xmlbeans/XmlObject;|52808
185|invokeinterface|923|java/util/Map.remove(Ljava/lang/Object;)Ljava/lang/Object;|52550
185|invokeinterface|25842|org/apache/xmlbeans/SchemaTypeLoader.parse(Lorg/apache/xmlbeans/xml/stream/XMLInputStream;Lorg/apache/xmlbeans/SchemaType;Lorg/apache/xmlbeans/XmlOptions;)Lorg/apache/xmlbeans/XmlObject;|52460
182|invokevirtual|432|java/io/ObjectInputStream.readObject()Ljava/lang/Object;|52425
185|invokeinterface|25840|org/apache/xmlbeans/SchemaTypeLoader.parse(Ljavax/xml/stream/XMLStreamReader;Lorg/apache/xmlbeans/SchemaType;Lorg/apache/xmlbeans/XmlOptions;)Lorg/apache/xmlbeans/XmlObject;|51980
182|invokevirtual|350|java/lang/reflect/Method.invoke(Ljava/lang/Object;[Ljava/lang/Object;)Ljava/lang/Object;|50791
192|checkcast|148|java/io/InputStream.close()V|49329
182|invokevirtual|895|java/util/ArrayList.toArray([Ljava/lang/Object;)[Ljava/lang/Object;|48711
185|invokeinterface|55595|java/util/concurrent/ConcurrentMap.get(Ljava/lang/Object;)Ljava/lang/Object;|48517
185|invokeinterface|25844|org/apache/xmlbeans/SchemaTypeSystem.resolveHandle(Ljava/lang/String;)Lorg/apache/xmlbeans/SchemaComponent;|47463
25|aload|12|java/lang/StringBuffer.<init>(Ljava/lang/String;)V|47292
184|invokestatic|67233|java/util/Arrays.copyOfRange([Ljava/lang/Object;II)[Ljava/lang/Object;|46713
182|invokevirtual|403833|scala/scalajs/js/Any$.fromFunction1(Lscala/Function1;)Lscala/scalajs/js/Function1;|45253
182|invokevirtual|71207|java/util/concurrent/ConcurrentHashMap.get(Ljava/lang/Object;)Ljava/lang/Object;|45036
0|nop|||44825
185|invokeinterface|3453877|org/jvnet/jaxb2_commons/lang/CopyStrategy.copy(Lorg/jvnet/jaxb2_commons/locator/ObjectLocator;Ljava/lang/Object;)Ljava/lang/Object;|44223
182|invokevirtual|61309|scala/Tuple3._3()Ljava/lang/Object;|43142
185|invokeinterface|56494|com/google/protobuf/Parser.parsePartialFrom(Lcom/google/protobuf/CodedInputStream;Lcom/google/protobuf/ExtensionRegistryLite;)Ljava/lang/Object;|43043
185|invokeinterface|56535|com/google/protobuf/Parser.parseFrom(Lcom/google/protobuf/ByteString;Lcom/google/protobuf/ExtensionRegistryLite;)Ljava/lang/Object;|42764
185|invokeinterface|56534|com/google/protobuf/Parser.parseFrom(Lcom/google/protobuf/ByteString;)Ljava/lang/Object;|42726
185|invokeinterface|56536|com/google/protobuf/Parser.parseFrom([B)Ljava/lang/Object;|42713
25|aload|13|java/lang/StringBuffer.append(Ljava/lang/Object;)Ljava/lang/StringBuffer;|42706
182|invokevirtual|56495|com/google/protobuf/InvalidProtocolBufferException.getUnfinishedMessage()Lcom/google/protobuf/MessageLite;|42705
185|invokeinterface|56537|com/google/protobuf/Parser.parseFrom([BLcom/google/protobuf/ExtensionRegistryLite;)Ljava/lang/Object;|42664
185|invokeinterface|81862|scala/collection/LinearSeqOptimized.apply(I)Ljava/lang/Object;|42117
